{"assets/.DS_Store":["assets/.DS_Store"],"assets/animation/coder.json":["assets/animation/coder.json"],"assets/animation/skills.json":["assets/animation/skills.json"],"assets/animation/yoga.json":["assets/animation/yoga.json"],"assets/back.jpeg":["assets/back.jpeg"],"assets/background.svg":["assets/background.svg"],"assets/burger_menu.svg":["assets/burger_menu.svg"],"assets/email.png":["assets/email.png"],"assets/fb.svg":["assets/fb.svg"],"assets/gdrive.svg":["assets/gdrive.svg"],"assets/gh.svg":["assets/gh.svg"],"assets/graphics/coder.svg":["assets/graphics/coder.svg"],"assets/graphics/skills.svg":["assets/graphics/skills.svg"],"assets/graphics/yoga.svg":["assets/graphics/yoga.svg"],"assets/in.svg":["assets/in.svg"],"assets/map.png":["assets/map.png"],"assets/phone.png":["assets/phone.png"],"assets/profile.jpeg":["assets/profile.jpeg"],"assets/profile_1.png":["assets/profile_1.png"],"assets/projects/habit.jpg":["assets/projects/habit.jpg"],"assets/projects/language.jpg":["assets/projects/language.jpg"],"assets/projects/shopping.jpg":["assets/projects/shopping.jpg"],"assets/projects/workout.jpg":["assets/projects/workout.jpg"],"assets/whatsapp.png":["assets/whatsapp.png"],"packages/cupertino_icons/assets/CupertinoIcons.ttf":["packages/cupertino_icons/assets/CupertinoIcons.ttf"],"packages/font_awesome_flutter/lib/fonts/fa-brands-400.ttf":["packages/font_awesome_flutter/lib/fonts/fa-brands-400.ttf"],"packages/font_awesome_flutter/lib/fonts/fa-regular-400.ttf":["packages/font_awesome_flutter/lib/fonts/fa-regular-400.ttf"],"packages/font_awesome_flutter/lib/fonts/fa-solid-900.ttf":["packages/font_awesome_flutter/lib/fonts/fa-solid-900.ttf"]}